aeppl/__init__.py
aeppl/_version.py
aeppl/abstract.py
aeppl/censoring.py
aeppl/convolutions.py
aeppl/cumsum.py
aeppl/dists.py
aeppl/joint_logprob.py
aeppl/logprob.py
aeppl/mixture.py
aeppl/printing.py
aeppl/rewriting.py
aeppl/scan.py
aeppl/tensor.py
aeppl/transforms.py
aeppl/utils.py
aeppl-0.1.5.dist-info/LICENSE
aeppl-0.1.5.dist-info/METADATA
aeppl-0.1.5.dist-info/WHEEL
aeppl-0.1.5.dist-info/top_level.txt
aeppl-0.1.5.dist-info/RECORD
